http_test_client.py
http_test_client-0.3.2.dist-info/DESCRIPTION.rst
http_test_client-0.3.2.dist-info/METADATA
http_test_client-0.3.2.dist-info/RECORD
http_test_client-0.3.2.dist-info/WHEEL
http_test_client-0.3.2.dist-info/metadata.json
http_test_client-0.3.2.dist-info/top_level.txt
