Metadata-Version: 1.1
Name: http_test_client
Version: 0.3.2
Summary: Library to simplify writing HTTP REST service integration tests
Home-page: https://github.com/maximkulkin/http-test-client
Author: Maxim Kulkin
Author-email: maxim.kulkin@gmail.com
License: MIT
Platform: UNKNOWN
Classifier: Development Status :: 4 - Beta
Classifier: Intended Audience :: Developers
Classifier: License :: OSI Approved :: MIT License
Classifier: Programming Language :: Python :: 2
Classifier: Programming Language :: Python :: 2.7
Classifier: Programming Language :: Python :: 3
Classifier: Programming Language :: Python :: 3.4
Classifier: Programming Language :: Python :: 3.5
Classifier: Programming Language :: Python :: 3.6
